[
  {
    "id": 1,
    "src": "https://images.unsplash.com/photo-1549931319-a545dcf3bc73?ixlib=rb-1.2.1&ixid=MnwxMjA3fDB8MHxwaG90by1wYWdlfHx8fGVufDB8fHx8&auto=format&fit=crop&w=1470&q=80",
    "name": "1무화과 호밀빵",
    "description": "천연효모를 사용하여 담백하고 무화과의 향이 잘 묻어나는 건강빵",
    "brand": "오월의 종",
    "nutrition": "나트륨: 340mg | 당류:15g | 포화지방:6g",
    "calorie": "200kcal",
    "price": 20000
  },
  {
    "id": 2,
    "src": "https://images.unsplash.com/photo-1549931319-a545dcf3bc73?ixlib=rb-1.2.1&ixid=MnwxMjA3fDB8MHxwaG90by1wYWdlfHx8fGVufDB8fHx8&auto=format&fit=crop&w=1470&q=80",
    "name": "2무화과 호밀빵",
    "description": "천연효모를 사용하여 담백하고 무화과의 향이 잘 묻어나는 건강빵",
    "brand": "오월의 종",
    "nutrition": "나트륨: 340mg | 당류:15g | 포화지방:6g",
    "calorie": "200kcal",
    "price": 20000
  },
  {
    "id": 3,
    "src": "https://images.unsplash.com/photo-1549931319-a545dcf3bc73?ixlib=rb-1.2.1&ixid=MnwxMjA3fDB8MHxwaG90by1wYWdlfHx8fGVufDB8fHx8&auto=format&fit=crop&w=1470&q=80",
    "name": "3무화과 호밀빵",
    "description": "천연효모를 사용하여 담백하고 무화과의 향이 잘 묻어나는 건강빵",
    "brand": "오월의 종",
    "nutrition": "나트륨: 340mg | 당류:15g | 포화지방:6g",
    "calorie": "200kcal",
    "price": 20000
  },
  {
    "id": 4,
    "src": "https://images.unsplash.com/photo-1549931319-a545dcf3bc73?ixlib=rb-1.2.1&ixid=MnwxMjA3fDB8MHxwaG90by1wYWdlfHx8fGVufDB8fHx8&auto=format&fit=crop&w=1470&q=80",
    "name": "4무화과 호밀빵",
    "description": "천연효모를 사용하여 담백하고 무화과의 향이 잘 묻어나는 건강빵",
    "brand": "오월의 종",
    "nutrition": "나트륨: 340mg | 당류:15g | 포화지방:6g",
    "calorie": "200kcal",
    "price": 20000
  },
  {
    "id": 5,
    "src": "https://images.unsplash.com/photo-1549931319-a545dcf3bc73?ixlib=rb-1.2.1&ixid=MnwxMjA3fDB8MHxwaG90by1wYWdlfHx8fGVufDB8fHx8&auto=format&fit=crop&w=1470&q=80",
    "name": "5무화과 호밀빵",
    "description": "천연효모를 사용하여 담백하고 무화과의 향이 잘 묻어나는 건강빵",
    "brand": "오월의 종",
    "nutrition": "나트륨: 340mg | 당류:15g | 포화지방:6g",
    "calorie": "200kcal",
    "price": 20000
  }
]
